pyGridSampler/__init__.py
pyGridSampler/grid_sampler.py
pyGridSampler/grid_tools.py
pyGridSampler-0.0.1.dist-info/LICENSE
pyGridSampler-0.0.1.dist-info/METADATA
pyGridSampler-0.0.1.dist-info/WHEEL
pyGridSampler-0.0.1.dist-info/top_level.txt
pyGridSampler-0.0.1.dist-info/RECORD
