Metadata-Version: 2.1
Name: pyGridSampler
Version: 0.0.1
Summary: Adaptive grid-based sampling with iterative batch sizes.
License-File: LICENSE
Requires-Dist: numpy (==1.23.3)
Requires-Dist: scipy (==1.9.0)
Requires-Dist: matplotlib (==3.5.2)
Requires-Dist: tqdm (==4.64.1)
